nc_console/__init__.py
nc_console/_console.py
nc_console/_logger.py
nc_console-0.1.0.dist-info/LICENSE
nc_console-0.1.0.dist-info/METADATA
nc_console-0.1.0.dist-info/WHEEL
nc_console-0.1.0.dist-info/top_level.txt
nc_console-0.1.0.dist-info/RECORD
