Metadata-Version: 2.1
Name: nc-console
Version: 0.1.0
Summary: The programmatic consoler.
Home-page: https://github.com/marktennyson/nc-console
Author: Aniket Sarkar
Author-email: aniketsarkar@yahoo.com
License: MIT
Keywords: console,input,logger,click,print,log,logging
Platform: any
Classifier: Development Status :: 5 - Production/Stable
Classifier: Intended Audience :: Developers
Classifier: License :: OSI Approved :: GNU General Public License v3 or later (GPLv3+)
Classifier: Operating System :: OS Independent
Classifier: Programming Language :: Python
Classifier: Programming Language :: Python :: 3
Classifier: Programming Language :: Python :: 3 :: Only
Classifier: Programming Language :: Python :: 3.6
Classifier: Programming Language :: Python :: 3.7
Classifier: Programming Language :: Python :: 3.8
Classifier: Programming Language :: Python :: 3.9
Classifier: Programming Language :: Python :: Implementation :: CPython
Classifier: Programming Language :: Python :: Implementation :: PyPy
Classifier: Topic :: Software Development :: Libraries :: Python Modules
Requires-Python: >=3.6,<4
License-File: LICENSE
Requires-Dist: click (>=8.0.0)
